bzrviews/__init__.py
bzrviews/helpers.py
bzrviews/models.py
bzrviews/settings.py
bzrviews/urls.py
bzrviews/views.py
django_bzrviews-0.0.2.dist-info/DESCRIPTION.rst
django_bzrviews-0.0.2.dist-info/METADATA
django_bzrviews-0.0.2.dist-info/RECORD
django_bzrviews-0.0.2.dist-info/WHEEL
django_bzrviews-0.0.2.dist-info/metadata.json
django_bzrviews-0.0.2.dist-info/top_level.txt
